iris_insee_utils/__init__.py
iris_insee_utils/get_iris_contours_data.py
iris_insee_utils/gps_coordinates_to_iris.py
iris_insee_utils/iris_map.py
iris_insee_utils/merge_geographical_info_to_iris_data.py
iris_insee_utils-0.1.1.dist-info/LICENSE
iris_insee_utils-0.1.1.dist-info/METADATA
iris_insee_utils-0.1.1.dist-info/WHEEL
iris_insee_utils-0.1.1.dist-info/top_level.txt
iris_insee_utils-0.1.1.dist-info/RECORD
