Metadata-Version: 2.1
Name: iris-insee-utils
Version: 0.1.1
Summary: Get code IRIS from GPS points or addresses
Author-email: adrienpacifico <adrienpacificopro@gmail.com>
Project-URL: Homepage, https://github.com/adrienpacifico/iris_insee_utils
Classifier: Development Status :: 4 - Beta
Classifier: Programming Language :: Python :: 3
Classifier: Programming Language :: Python :: 3.12
Classifier: Intended Audience :: Developers
Classifier: License :: OSI Approved :: GNU General Public License v3 (GPLv3)
Requires-Python: >=3.10
License-File: LICENSE
Requires-Dist: folium >=0.18.0
Requires-Dist: geopandas >=1.0.1
Requires-Dist: loguru >=0.7.2
Requires-Dist: matplotlib >=3.9.2
Requires-Dist: py7zr >=0.22.0
Requires-Dist: pyarrow >=18.0.0
Requires-Dist: pylint >=3.3.1
Requires-Dist: pytest-cov >=6.0.0
Requires-Dist: pytest-xdist >=3.6.1
Requires-Dist: requests >=2.32.3
Requires-Dist: tqdm >=4.66.6
